{
  "beacon": "[1ere][sujets0][gén][sujet-2][automatismes][question-7]",
  "statement": "Le plan est muni d'un repère orthogonal. On note $d$ la droite passant par les points $A(-40;39)$ et $B(51;-67)$. Calculer le coefficient directeur de la droite $d$.",
  "statement_html": "<div>Le plan est muni d'un repère orthogonal. On note $d$ la droite passant par les points $A(-40;39)$ et $B(51;-67)$. Calculer le coefficient directeur de la droite $d$.</div>",
  "answer": {
    "latex": "\\dfrac{-67 -39}{51 + 40}",
    "simplified_latex": "-\\dfrac{106}{91}",
    "sympy_exp_data": {
      "type": "Mul",
      "sp.srepr": "Mul(Add(Integer(-67), Integer(-39)), Pow(Add(Integer(40), Integer(51)), Integer(-1)))",
      "str": "(-67 - 39)/(40 + 51)"
    },
    "formal_repr": "Fraction(p=Add(l=Integer(n=-67), r=Integer(n=-39)), q=Add(l=Integer(n=51), r=Integer(n=40)))"
  },
  "components": {
    "x1": "-40",
    "y1": "39",
    "x2": "51",
    "y2": "-67"
  },
  "seed": 3,
  "generator": "gen_sujet2_auto_06_question",
  "success": true,
  "stdout": "",
  "stderr": ""
}