{
  "beacon": "[1ere][sujets0][spé][sujet-1][automatismes][question-12]",
  "statement": "Voici une série de notes avec les coefficients associés\n-6 coefficient 1\n-0 coefficient 2\n-16 coefficient $x$\nOn note $m$ la moyenne de cette série. Que doit valoir $x$ pour que $m = 7.6$ ?",
  "answer": {
    "latex": "2",
    "simplified_latex": "2",
    "sympy_exp_data": {
      "type": "Integer",
      "sp.srepr": "Integer(2)",
      "str": "2"
    },
    "formal_repr": "Integer(n=2)"
  },
  "components": {
    "note1": "6",
    "note2": "0",
    "note3": "16",
    "coef1": "1",
    "coef2": "2",
    "coef3": "2",
    "mean": "\\dfrac{6 \\times 1 + 0 \\times 2 + 16 \\times 2}{1 + 2 + 2}"
  },
  "seed": 15,
  "generator": "spe_sujet1_auto_12_question",
  "success": true,
  "stdout": "",
  "stderr": ""
}