{
  "beacon": "[1ere][sujets0][spé][sujet-2][automatismes][question-10]",
  "statement": "La fonction ${f}$ définie sur $\\\\mathbb\\{R\\}$ par $f(x) = \\left(-8x -2\\right) \\times \\left(9x -6\\right)$. Quel est le signe de f sur l'intervalle $\\lbracket -\\dfrac{6}{9}; --\\dfrac{2}{-8}\\rbracket$ ?",
  "answer": {
    "latex": "f(x) > 0",
    "simplified_latex": "f(x) > 0",
    "sympy_exp_data": {
      "type": "StrictGreaterThan",
      "sp.srepr": "StrictGreaterThan(Function('f')(Symbol('x')), Integer(0))",
      "str": "f(x) > 0"
    },
    "formal_repr": "StrictGreaterThan(l=Function(name=f)(Symbol(s='x')), r=Integer(n=0))"
  },
  "components": {
    "root1": "-\\dfrac{6}{9}",
    "root2": "--\\dfrac{2}{-8}",
    "a1": "-8",
    "a2": "9",
    "b1": "-2",
    "b2": "-6",
    "interval": "\\lbracket -\\dfrac{6}{9}; --\\dfrac{2}{-8}\\rbracket",
    "x": "x",
    "f": "f"
  },
  "seed": 89,
  "generator": "spe_sujet2_auto_10_question",
  "success": true,
  "stdout": "",
  "stderr": ""
}