{
  "beacon": "[1ere][sujets0][gen][sujet-2][automatismes][question-2]",
  "statement": "Calculer $10 \\%$ de $370$.",
  "mask": "",
  "answer": {
    "latex": "\\dfrac{2}{20}370",
    "simplified_latex": "37",
    "sympy_exp_data": {
      "type": "Mul",
      "sp.srepr": "Mul(Rational(1, 10), Integer(370))",
      "str": "(1/10)*370"
    },
    "formal_repr": "Mul(l=Fraction(p=Integer(n=2), q=Integer(n=20)), r=Integer(n=370))"
  },
  "components": {
    "n": "370",
    "x": "\\dfrac{2}{20}"
  },
  "seed": 10,
  "generator": "gen_sujet1_auto_01_question",
  "success": true,
  "stdout": "",
  "stderr": ""
}