{
  "beacon": "[1ere][sujets0][gén][sujet-3][automatismes][question-7]",
  "statement": "6 articles coûtent 10.2 euros. Combien coûtent 14 articles ?",
  "answer": {
    "latex": "\\dfrac{17}{10} \\times 14",
    "simplified_latex": "\\dfrac{119}{5}",
    "sympy_exp_data": {
      "type": "Mul",
      "sp.srepr": "Mul(Rational(17, 10), Integer(14))",
      "str": "(17/10)*14"
    },
    "formal_repr": "Mul(l=Fraction(p=Integer(n=17), q=Integer(n=10)), r=Integer(n=14))"
  },
  "components": {
    "n1": "6",
    "n2": "14",
    "p": "\\dfrac{17}{10}"
  },
  "seed": 47,
  "generator": "gen_sujet3_auto_07_question",
  "success": true,
  "stdout": "",
  "stderr": ""
}