{
  "beacon": "[1ere][sujets0][gén][sujet-2][automatismes][question-08]",
  "statement": "Développer $\\left(x + 3\\right) \\times \\left(-5x -8\\right)$.",
  "statement_html": "<div>Développer $\\left(x + 3\\right) \\times \\left(-5x -8\\right)$.</div>",
  "answer": {
    "latex": "-5x^{2} -23x -24",
    "simplified_latex": "-5x^{2} -23x -24",
    "sympy_exp_data": {
      "type": "Add",
      "sp.srepr": "Add(Mul(Integer(-1), Integer(5), Pow(Symbol('x'), Integer(2))), Add(Mul(Integer(-1), Integer(23), Symbol('x')), Integer(-24)))",
      "str": "-5*x**2 + (-23*x - 24)"
    },
    "formal_repr": "Add(l=Mul(l=Integer(n=-5), r=Pow(base=Symbol(s='x'), exp=Integer(n=2))), r=Add(l=Mul(l=Integer(n=-23), r=Symbol(s='x')), r=Integer(n=-24)))"
  },
  "components": {
    "x": "x",
    "a1": "1",
    "b1": "3",
    "a2": "-5",
    "b2": "-8",
    "expr": "\\left(x + 3\\right) \\times \\left(-5x -8\\right)"
  },
  "seed": 7,
  "generator": "gen_sujet2_auto_08_question",
  "success": true,
  "stdout": "",
  "stderr": ""
}