{
  "beacon": "[1ere][sujets0][spé][sujet-2][automatismes][question-12]",
  "statement": "Si un point mobile suit une trajectoire circulaire de rayon $R$, en mètre ($m$), son accélération centripète $u$ (en $m/s^2$) s'exprime en fonction de la vitesse $v$ (en $m/s$) de la manière suivante: $$a = \\dfrac{v^{2}}{R}$$ Exprimer $v$ en fonction de a et R.",
  "answer": {
    "latex": "\\left(aR\\right)^{\\dfrac{1}{2}}",
    "simplified_latex": "\\left(aR\\right)^{\\dfrac{1}{2}}",
    "sympy_exp_data": {
      "type": "Pow",
      "sp.srepr": "Pow(Mul(Symbol('R'), Symbol('a')), Rational(1, 2))",
      "str": "sqrt(R*a)"
    },
    "formal_repr": "Pow(base=Mul(l=Symbol(s='a'), r=Symbol(s='R')), exp=Fraction(p=Integer(n=1), q=Integer(n=2)))"
  },
  "components": {
    "v": "v",
    "a": "a",
    "r": "R",
    "expr": "a = \\dfrac{v^{2}}{R}"
  },
  "seed": 1,
  "generator": "spe_sujet2_auto_12_question",
  "success": true,
  "stdout": "",
  "stderr": ""
}